jaitool/__init__.py
jaitool/annotation/__init__.py
jaitool/annotation/change_background.py
jaitool/annotation/ndds2coco.py
jaitool/annotation/ue_to_coco_tropicana.py
jaitool/annotation/vis_data.py
jaitool/annotation/COCO/__init__.py
jaitool/annotation/COCO/coco_dataset.py
jaitool/annotation/COCO/coco_result_dataset.py
jaitool/annotation/COCO/edit_coco_json.py
jaitool/annotation/COCO/split_coco.py
jaitool/annotation/COCO/vis_ann.py
jaitool/annotation/DET2/__init__.py
jaitool/annotation/DET2/dataset.py
jaitool/annotation/Labelme/__init__.py
jaitool/annotation/Labelme/main.py
jaitool/annotation/NDDS/__init__.py
jaitool/annotation/NDDS/fetch_ndds_info.py
jaitool/annotation/NDDS/merge_objects.py
jaitool/aug/__init__.py
jaitool/aug/aug_visualizer.py
jaitool/aug/augment.py
jaitool/aug/augment_loader.py
jaitool/draw/__init__.py
jaitool/draw/drawing_utils.py
jaitool/evaluation/__init__.py
jaitool/evaluation/evaluator.py
jaitool/graph/__init__.py
jaitool/graph/plot.py
jaitool/inference/__init__.py
jaitool/inference/d2_infer.py
jaitool/inference/models/__init__.py
jaitool/inference/models/hook/__init__.py
jaitool/inference/models/hook/hook.py
jaitool/inference/models/hook/hook_utils.py
jaitool/structures/__init__.py
jaitool/structures/bbox.py
jaitool/structures/keypoint.py
jaitool/structures/point.py
jaitool/structures/segmentation.py
jaitool/training/__init__.py
jaitool/training/saving_model.py
jaitool/training/train_multi_val_key_seg.py
jaitool/training/training.py
jaitool-0.1.9.dist-info/LICENSE
jaitool-0.1.9.dist-info/METADATA
jaitool-0.1.9.dist-info/WHEEL
jaitool-0.1.9.dist-info/top_level.txt
jaitool-0.1.9.dist-info/RECORD
